uuid64.py
temporaluuid64-0.2.0.dist-info/METADATA
temporaluuid64-0.2.0.dist-info/WHEEL
temporaluuid64-0.2.0.dist-info/top_level.txt
temporaluuid64-0.2.0.dist-info/RECORD
