Metadata-Version: 2.1
Name: temporaluuid64
Version: 0.2.0
Summary: A time-based 64-bit UUID generator
Home-page: https://github.com/suminb/temporaluuid64
Author: Sumin Byeon
Author-email: suminb@gmail.com
